pixtra/__init__.py
pixtra-0.0.0.dist-info/LICENSE
pixtra-0.0.0.dist-info/METADATA
pixtra-0.0.0.dist-info/WHEEL
pixtra-0.0.0.dist-info/top_level.txt
pixtra-0.0.0.dist-info/RECORD
